{"stats":{"minecraft:dropped":{"minecraft:string":65},"minecraft:custom":{"minecraft:jump":7,"minecraft:time_since_rest":4799,"minecraft:leave_game":1,"minecraft:crouch_one_cm":19,"minecraft:sprint_one_cm":1510,"minecraft:play_time":4799,"minecraft:time_since_death":4799,"minecraft:walk_one_cm":862,"minecraft:sneak_time":18,"minecraft:total_world_time":4799,"minecraft:drop":2,"minecraft:fly_one_cm":4416},"minecraft:used":{"minecraft:end_portal_frame":1},"minecraft:picked_up":{"gitsnshiggles:void_string":64,"minecraft:string":1}},"DataVersion":3955}